ovos_tts_plugin_deepponies/__init__.py
ovos_tts_plugin_deepponies/deepponies.py
ovos_tts_plugin_deepponies/version.py
ovos_tts_plugin_deepponies/assets/lexicon.txt
ovos_tts_plugin_deepponies/assets/speakerCategories.json
ovos_tts_plugin_deepponies/assets/symbol2id.json
ovos_tts_plugin_deepponies-0.0.2.dist-info/LICENSE
ovos_tts_plugin_deepponies-0.0.2.dist-info/METADATA
ovos_tts_plugin_deepponies-0.0.2.dist-info/WHEEL
ovos_tts_plugin_deepponies-0.0.2.dist-info/entry_points.txt
ovos_tts_plugin_deepponies-0.0.2.dist-info/top_level.txt
ovos_tts_plugin_deepponies-0.0.2.dist-info/zip-safe
ovos_tts_plugin_deepponies-0.0.2.dist-info/RECORD
