Metadata-Version: 2.1
Name: ovos-tts-plugin-deepponies
Version: 0.0.2
Summary: deepponies tts plugin for OpenVoiceOS
Home-page: https://github.com/OpenVoiceOS/ovos-tts-plugin-deepponies
Author: JarbasAi
Author-email: jarbasai@mailfence.com
License: Apache-2.0
Keywords: mycroft plugin tts OVOS OpenVoiceOS
Platform: UNKNOWN
Classifier: Development Status :: 3 - Alpha
Classifier: Intended Audience :: Developers
Classifier: Topic :: Text Processing :: Linguistic
Classifier: License :: OSI Approved :: Apache Software License
Classifier: Programming Language :: Python :: 3.7
Classifier: Programming Language :: Python :: 3.8
Classifier: Programming Language :: Python :: 3.9
Requires-Dist: torch (==1.10.0)
Requires-Dist: transformers
Requires-Dist: g2p-en (==2.0.0)
Requires-Dist: nltk (==3.6.5)
Requires-Dist: Cython
Requires-Dist: nemo-toolkit (==1.5.1)
Requires-Dist: pynini (==2.1.4)
Requires-Dist: soundfile
